Mitra/__init__.py
Mitra/MatErr/__init__.py
Mitra/leq/__init__.py
Mitra-1.0.4.dist-info/METADATA
Mitra-1.0.4.dist-info/RECORD
Mitra-1.0.4.dist-info/WHEEL
Mitra-1.0.4.dist-info/top_level.txt
