Metadata-Version: 2.1
Name: Mitra
Version: 1.0.4
Summary: Provides basic operatons of Matrix and solve system of linear equations using Matrix. It also finds eigenvalues of Square Matrix.
Home-page: https://github.com/rdsquare/Mitra.git
Author: Rahul Dangi & Som Durgesh Gupta
Author-email: rdsquare144@gmail.com
License: GNU General Public License, Version 3
Platform: UNKNOWN
Classifier: Intended Audience :: Developers
Classifier: Intended Audience :: Science/Research
Classifier: Intended Audience :: End Users/Desktop
Classifier: Intended Audience :: Other Audience
Classifier: Intended Audience :: Developers
Classifier: Topic :: Software Development :: Libraries
Classifier: License :: OSI Approved
Classifier: Programming Language :: Python :: 3
Classifier: Programming Language :: Python :: 2.7
Classifier: Operating System :: OS Independent
